<?xml version="1.0" encoding="UTF-8"?>

<!-- generated on 2026-07-17 15:10:30 by Eclipse SUMO sumo Version 1.20.0
<configuration xmlns:xsi="http://www.w3.org/2001/XMLSchema-instance" xsi:noNamespaceSchemaLocation="http://sumo.dlr.de/xsd/sumoConfiguration.xsd">

    <input>
        <net-file value="net.net.xml"/>
        <route-files value="rou.rou.xml"/>
    </input>

    <output>
        <precision value="6"/>
        <fcd-output value="golden.fcd.xml"/>
        <fcd-output.acceleration value="true"/>
        <summary-output value="golden.summary.xml"/>
        <statistic-output value="golden.statistic.xml"/>
        <save-state.times value="1"/>
        <save-state.files value="golden.state.xml"/>
    </output>

    <time>
        <begin value="0"/>
        <end value="300"/>
        <step-length value="1"/>
    </time>

    <processing>
        <step-method.ballistic value="false"/>
        <collision.action value="none"/>
        <time-to-teleport value="-1"/>
        <default.action-step-length value="1"/>
        <default.speeddev value="0"/>
    </processing>

    <routing>
        <routing-algorithm value="astar"/>
        <device.rerouting.probability value="1.0"/>
        <device.rerouting.period value="30"/>
        <device.rerouting.adaptation-steps value="18"/>
    </routing>

    <report>
        <no-step-log value="true"/>
    </report>

    <random_number>
        <seed value="42"/>
    </random_number>

</configuration>
-->

<summary xmlns:xsi="http://www.w3.org/2001/XMLSchema-instance" xsi:noNamespaceSchemaLocation="http://sumo.dlr.de/xsd/summary_file.xsd">
    <step time="0.000" loaded="1" inserted="1" running="1" waiting="0" ended="0" arrived="0" collisions="0" teleports="0" halting="1" stopped="0" meanWaitingTime="0.000000" meanTravelTime="-1.000000" meanSpeed="0.000000" meanSpeedRelative="0.000000" duration="2"/>
    <step time="1.000" loaded="1" inserted="1" running="1" waiting="0" ended="0" arrived="0" collisions="0" teleports="0" halting="0" stopped="0" meanWaitingTime="0.000000" meanTravelTime="-1.000000" meanSpeed="2.600000" meanSpeedRelative="0.187185" duration="2"/>
    <step time="2.000" loaded="1" inserted="1" running="1" waiting="0" ended="0" arrived="0" collisions="0" teleports="0" halting="0" stopped="0" meanWaitingTime="0.000000" meanTravelTime="-1.000000" meanSpeed="5.200000" meanSpeedRelative="0.374370" duration="0"/>
    <step time="3.000" loaded="2" inserted="2" running="2" waiting="0" ended="0" arrived="0" collisions="0" teleports="0" halting="1" stopped="0" meanWaitingTime="0.000000" meanTravelTime="-1.000000" meanSpeed="3.900000" meanSpeedRelative="0.280778" duration="0"/>
    <step time="4.000" loaded="2" inserted="2" running="2" waiting="0" ended="0" arrived="0" collisions="0" teleports="0" halting="0" stopped="0" meanWaitingTime="0.000000" meanTravelTime="-1.000000" meanSpeed="6.500000" meanSpeedRelative="0.467963" duration="0"/>
    <step time="5.000" loaded="2" inserted="2" running="2" waiting="0" ended="0" arrived="0" collisions="0" teleports="0" halting="0" stopped="0" meanWaitingTime="0.000000" meanTravelTime="-1.000000" meanSpeed="9.100000" meanSpeedRelative="0.655148" duration="0"/>
    <step time="6.000" loaded="3" inserted="3" running="3" waiting="0" ended="0" arrived="0" collisions="0" teleports="0" halting="1" stopped="0" meanWaitingTime="0.000000" meanTravelTime="-1.000000" meanSpeed="7.230000" meanSpeedRelative="0.520518" duration="0"/>
    <step time="7.000" loaded="3" inserted="3" running="3" waiting="0" ended="0" arrived="0" collisions="0" teleports="0" halting="0" stopped="0" meanWaitingTime="0.000000" meanTravelTime="-1.000000" meanSpeed="8.963333" meanSpeedRelative="0.645308" duration="0"/>
    <step time="8.000" loaded="3" inserted="3" running="3" waiting="0" ended="0" arrived="0" collisions="0" teleports="0" halting="0" stopped="0" meanWaitingTime="0.000000" meanTravelTime="-1.000000" meanSpeed="10.696667" meanSpeedRelative="0.770098" duration="0"/>
    <step time="9.000" loaded="4" inserted="4" running="4" waiting="0" ended="0" arrived="0" collisions="0" teleports="0" halting="1" stopped="0" meanWaitingTime="0.000000" meanTravelTime="-1.000000" meanSpeed="8.895000" meanSpeedRelative="0.640389" duration="0"/>
    <step time="10.000" loaded="4" inserted="4" running="4" waiting="0" ended="0" arrived="0" collisions="0" teleports="0" halting="0" stopped="0" meanWaitingTime="0.000000" meanTravelTime="-1.000000" meanSpeed="10.195000" meanSpeedRelative="0.733981" duration="0"/>
    <step time="11.000" loaded="4" inserted="4" running="4" waiting="0" ended="0" arrived="0" collisions="0" teleports="0" halting="0" stopped="0" meanWaitingTime="0.000000" meanTravelTime="-1.000000" meanSpeed="11.495000" meanSpeedRelative="0.827574" duration="0"/>
    <step time="12.000" loaded="5" inserted="5" running="5" waiting="0" ended="0" arrived="0" collisions="0" teleports="0" halting="1" stopped="0" meanWaitingTime="0.000000" meanTravelTime="-1.000000" meanSpeed="9.894000" meanSpeedRelative="0.712311" duration="1"/>
    <step time="13.000" loaded="5" inserted="5" running="5" waiting="0" ended="0" arrived="0" collisions="0" teleports="0" halting="0" stopped="0" meanWaitingTime="0.000000" meanTravelTime="-1.000000" meanSpeed="10.934000" meanSpeedRelative="0.787185" duration="0"/>
    <step time="14.000" loaded="5" inserted="5" running="5" waiting="0" ended="0" arrived="0" collisions="0" teleports="0" halting="0" stopped="0" meanWaitingTime="0.000000" meanTravelTime="-1.000000" meanSpeed="11.974000" meanSpeedRelative="0.862059" duration="0"/>
    <step time="15.000" loaded="6" inserted="6" running="6" waiting="0" ended="0" arrived="0" collisions="0" teleports="0" halting="1" stopped="0" meanWaitingTime="0.000000" meanTravelTime="-1.000000" meanSpeed="10.560000" meanSpeedRelative="0.760259" duration="0"/>
    <step time="16.000" loaded="6" inserted="6" running="6" waiting="0" ended="0" arrived="0" collisions="0" teleports="0" halting="0" stopped="0" meanWaitingTime="0.000000" meanTravelTime="-1.000000" meanSpeed="11.426667" meanSpeedRelative="0.822654" duration="0"/>
    <step time="17.000" loaded="6" inserted="6" running="6" waiting="0" ended="0" arrived="0" collisions="0" teleports="0" halting="0" stopped="0" meanWaitingTime="0.000000" meanTravelTime="-1.000000" meanSpeed="12.293333" meanSpeedRelative="0.885049" duration="0"/>
    <step time="18.000" loaded="7" inserted="7" running="7" waiting="0" ended="0" arrived="0" collisions="0" teleports="0" halting="1" stopped="0" meanWaitingTime="0.000000" meanTravelTime="-1.000000" meanSpeed="11.035714" meanSpeedRelative="0.794508" duration="0"/>
    <step time="19.000" loaded="7" inserted="7" running="7" waiting="0" ended="0" arrived="0" collisions="0" teleports="0" halting="0" stopped="0" meanWaitingTime="0.000000" meanTravelTime="-1.000000" meanSpeed="11.778571" meanSpeedRelative="0.847989" duration="0"/>
    <step time="20.000" loaded="7" inserted="7" running="7" waiting="0" ended="0" arrived="0" collisions="0" teleports="0" halting="0" stopped="0" meanWaitingTime="0.000000" meanTravelTime="-1.000000" meanSpeed="12.521429" meanSpeedRelative="0.901471" duration="0"/>
    <step time="21.000" loaded="8" inserted="8" running="8" waiting="0" ended="0" arrived="0" collisions="0" teleports="0" halting="1" stopped="0" meanWaitingTime="0.000000" meanTravelTime="-1.000000" meanSpeed="11.392500" meanSpeedRelative="0.820194" duration="0"/>
    <step time="22.000" loaded="8" inserted="8" running="8" waiting="0" ended="0" arrived="0" collisions="0" teleports="0" halting="0" stopped="0" meanWaitingTime="0.000000" meanTravelTime="-1.000000" meanSpeed="12.042500" meanSpeedRelative="0.866991" duration="0"/>
    <step time="23.000" loaded="8" inserted="8" running="8" waiting="0" ended="0" arrived="0" collisions="0" teleports="0" halting="0" stopped="0" meanWaitingTime="0.000000" meanTravelTime="-1.000000" meanSpeed="12.692500" meanSpeedRelative="0.913787" duration="1"/>
    <step time="24.000" loaded="9" inserted="9" running="9" waiting="0" ended="0" arrived="0" collisions="0" teleports="0" halting="1" stopped="0" meanWaitingTime="0.000000" meanTravelTime="-1.000000" meanSpeed="11.670000" meanSpeedRelative="0.840173" duration="0"/>
    <step time="25.000" loaded="9" inserted="9" running="9" waiting="0" ended="0" arrived="0" collisions="0" teleports="0" halting="0" stopped="0" meanWaitingTime="0.000000" meanTravelTime="-1.000000" meanSpeed="12.247778" meanSpeedRelative="0.881769" duration="0"/>
    <step time="26.000" loaded="9" inserted="9" running="9" waiting="0" ended="0" arrived="0" collisions="0" teleports="0" halting="0" stopped="0" meanWaitingTime="0.000000" meanTravelTime="-1.000000" meanSpeed="12.825556" meanSpeedRelative="0.923366" duration="0"/>
    <step time="27.000" loaded="10" inserted="10" running="10" waiting="0" ended="0" arrived="0" collisions="0" teleports="0" halting="1" stopped="0" meanWaitingTime="0.000000" meanTravelTime="-1.000000" meanSpeed="11.892000" meanSpeedRelative="0.856156" duration="0"/>
    <step time="28.000" loaded="10" inserted="10" running="10" waiting="0" ended="0" arrived="0" collisions="0" teleports="0" halting="0" stopped="0" meanWaitingTime="0.000000" meanTravelTime="-1.000000" meanSpeed="12.412000" meanSpeedRelative="0.893593" duration="0"/>
    <step time="29.000" loaded="10" inserted="10" running="10" waiting="0" ended="0" arrived="0" collisions="0" teleports="0" halting="0" stopped="0" meanWaitingTime="0.000000" meanTravelTime="-1.000000" meanSpeed="12.932000" meanSpeedRelative="0.931030" duration="0"/>
    <step time="30.000" loaded="11" inserted="11" running="11" waiting="0" ended="0" arrived="0" collisions="0" teleports="0" halting="1" stopped="0" meanWaitingTime="0.000000" meanTravelTime="-1.000000" meanSpeed="12.073636" meanSpeedRelative="0.869232" duration="0"/>
    <step time="31.000" loaded="11" inserted="11" running="11" waiting="0" ended="0" arrived="0" collisions="0" teleports="0" halting="0" stopped="0" meanWaitingTime="0.000000" meanTravelTime="-1.000000" meanSpeed="12.546364" meanSpeedRelative="0.903266" duration="0"/>
    <step time="32.000" loaded="11" inserted="11" running="11" waiting="0" ended="0" arrived="0" collisions="0" teleports="0" halting="0" stopped="0" meanWaitingTime="0.000000" meanTravelTime="-1.000000" meanSpeed="13.019091" meanSpeedRelative="0.937300" duration="0"/>
    <step time="33.000" loaded="12" inserted="12" running="12" waiting="0" ended="0" arrived="0" collisions="0" teleports="0" halting="1" stopped="0" meanWaitingTime="0.000000" meanTravelTime="-1.000000" meanSpeed="12.225000" meanSpeedRelative="0.880130" duration="0"/>
    <step time="34.000" loaded="12" inserted="12" running="12" waiting="0" ended="0" arrived="0" collisions="0" teleports="0" halting="0" stopped="0" meanWaitingTime="0.000000" meanTravelTime="-1.000000" meanSpeed="12.658333" meanSpeedRelative="0.911327" duration="0"/>
    <step time="35.000" loaded="12" inserted="12" running="12" waiting="0" ended="0" arrived="0" collisions="0" teleports="0" halting="0" stopped="0" meanWaitingTime="0.000000" meanTravelTime="-1.000000" meanSpeed="13.091667" meanSpeedRelative="0.942525" duration="0"/>
    <step time="36.000" loaded="13" inserted="13" running="13" waiting="0" ended="0" arrived="0" collisions="0" teleports="0" halting="1" stopped="0" meanWaitingTime="0.000000" meanTravelTime="-1.000000" meanSpeed="12.353077" meanSpeedRelative="0.889350" duration="0"/>
    <step time="37.000" loaded="13" inserted="13" running="13" waiting="0" ended="0" arrived="0" collisions="0" teleports="0" halting="0" stopped="0" meanWaitingTime="0.000000" meanTravelTime="-1.000000" meanSpeed="12.753077" meanSpeedRelative="0.918148" duration="0"/>
    <step time="38.000" loaded="13" inserted="13" running="13" waiting="0" ended="0" arrived="0" collisions="0" teleports="0" halting="0" stopped="0" meanWaitingTime="0.000000" meanTravelTime="-1.000000" meanSpeed="13.153077" meanSpeedRelative="0.946946" duration="0"/>
    <step time="39.000" loaded="14" inserted="14" running="14" waiting="0" ended="0" arrived="0" collisions="0" teleports="0" halting="1" stopped="0" meanWaitingTime="0.000000" meanTravelTime="-1.000000" meanSpeed="12.462857" meanSpeedRelative="0.897254" duration="0"/>
    <step time="40.000" loaded="14" inserted="14" running="14" waiting="0" ended="0" arrived="0" collisions="0" teleports="0" halting="0" stopped="0" meanWaitingTime="0.000000" meanTravelTime="-1.000000" meanSpeed="12.834286" meanSpeedRelative="0.923995" duration="0"/>
    <step time="41.000" loaded="14" inserted="14" running="14" waiting="0" ended="0" arrived="0" collisions="0" teleports="0" halting="0" stopped="0" meanWaitingTime="0.000000" meanTravelTime="-1.000000" meanSpeed="13.205714" meanSpeedRelative="0.950735" duration="0"/>
    <step time="42.000" loaded="15" inserted="15" running="15" waiting="0" ended="0" arrived="0" collisions="0" teleports="0" halting="1" stopped="0" meanWaitingTime="0.000000" meanTravelTime="-1.000000" meanSpeed="12.558000" meanSpeedRelative="0.904104" duration="0"/>
    <step time="43.000" loaded="15" inserted="15" running="15" waiting="0" ended="0" arrived="0" collisions="0" teleports="0" halting="0" stopped="0" meanWaitingTime="0.000000" meanTravelTime="-1.000000" meanSpeed="12.904667" meanSpeedRelative="0.929062" duration="0"/>
    <step time="44.000" loaded="15" inserted="15" running="15" waiting="0" ended="0" arrived="0" collisions="0" teleports="0" halting="0" stopped="0" meanWaitingTime="0.000000" meanTravelTime="-1.000000" meanSpeed="13.251333" meanSpeedRelative="0.954020" duration="0"/>
    <step time="45.000" loaded="16" inserted="16" running="16" waiting="0" ended="0" arrived="0" collisions="0" teleports="0" halting="1" stopped="0" meanWaitingTime="0.000000" meanTravelTime="-1.000000" meanSpeed="12.641250" meanSpeedRelative="0.910097" duration="0"/>
    <step time="46.000" loaded="16" inserted="16" running="16" waiting="0" ended="0" arrived="0" collisions="0" teleports="0" halting="0" stopped="0" meanWaitingTime="0.000000" meanTravelTime="-1.000000" meanSpeed="12.791250" meanSpeedRelative="0.920896" duration="0"/>
    <step time="47.000" loaded="16" inserted="16" running="16" waiting="0" ended="0" arrived="0" collisions="0" teleports="0" halting="0" stopped="0" meanWaitingTime="0.000000" meanTravelTime="-1.000000" meanSpeed="13.278750" meanSpeedRelative="0.955994" duration="0"/>
    <step time="48.000" loaded="17" inserted="17" running="17" waiting="0" ended="0" arrived="0" collisions="0" teleports="0" halting="1" stopped="0" meanWaitingTime="0.000000" meanTravelTime="-1.000000" meanSpeed="12.714706" meanSpeedRelative="0.915386" duration="0"/>
    <step time="49.000" loaded="17" inserted="17" running="17" waiting="0" ended="0" arrived="0" collisions="0" teleports="0" halting="0" stopped="0" meanWaitingTime="0.000000" meanTravelTime="-1.000000" meanSpeed="12.855882" meanSpeedRelative="0.925549" duration="1"/>
    <step time="50.000" loaded="17" inserted="17" running="17" waiting="0" ended="0" arrived="0" collisions="0" teleports="0" halting="0" stopped="0" meanWaitingTime="0.000000" meanTravelTime="-1.000000" meanSpeed="13.314706" meanSpeedRelative="0.958582" duration="0"/>
    <step time="51.000" loaded="18" inserted="18" running="18" waiting="0" ended="0" arrived="0" collisions="0" teleports="0" halting="1" stopped="0" meanWaitingTime="0.000000" meanTravelTime="-1.000000" meanSpeed="12.780000" meanSpeedRelative="0.920086" duration="0"/>
    <step time="52.000" loaded="18" inserted="18" running="18" waiting="0" ended="0" arrived="0" collisions="0" teleports="0" halting="0" stopped="0" meanWaitingTime="0.000000" meanTravelTime="-1.000000" meanSpeed="12.913333" meanSpeedRelative="0.929686" duration="0"/>
    <step time="53.000" loaded="18" inserted="18" running="18" waiting="0" ended="0" arrived="0" collisions="0" teleports="0" halting="0" stopped="0" meanWaitingTime="0.000000" meanTravelTime="-1.000000" meanSpeed="13.346667" meanSpeedRelative="0.960883" duration="0"/>
    <step time="54.000" loaded="19" inserted="19" running="19" waiting="0" ended="0" arrived="0" collisions="0" teleports="0" halting="1" stopped="0" meanWaitingTime="0.000000" meanTravelTime="-1.000000" meanSpeed="12.838421" meanSpeedRelative="0.924292" duration="0"/>
    <step time="55.000" loaded="19" inserted="19" running="19" waiting="0" ended="0" arrived="0" collisions="0" teleports="0" halting="0" stopped="0" meanWaitingTime="0.000000" meanTravelTime="-1.000000" meanSpeed="12.964737" meanSpeedRelative="0.933386" duration="0"/>
    <step time="56.000" loaded="19" inserted="19" running="19" waiting="0" ended="0" arrived="0" collisions="0" teleports="0" halting="0" stopped="0" meanWaitingTime="0.000000" meanTravelTime="-1.000000" meanSpeed="13.375263" meanSpeedRelative="0.962942" duration="0"/>
    <step time="57.000" loaded="20" inserted="20" running="20" waiting="0" ended="0" arrived="0" collisions="0" teleports="0" halting="1" stopped="0" meanWaitingTime="0.000000" meanTravelTime="-1.000000" meanSpeed="12.891000" meanSpeedRelative="0.928078" duration="0"/>
    <step time="58.000" loaded="20" inserted="20" running="20" waiting="0" ended="0" arrived="0" collisions="0" teleports="0" halting="0" stopped="0" meanWaitingTime="0.000000" meanTravelTime="-1.000000" meanSpeed="13.011000" meanSpeedRelative="0.936717" duration="0"/>
    <step time="59.000" loaded="20" inserted="20" running="20" waiting="0" ended="0" arrived="0" collisions="0" teleports="0" halting="0" stopped="0" meanWaitingTime="0.000000" meanTravelTime="-1.000000" meanSpeed="13.401000" meanSpeedRelative="0.964795" duration="0"/>
    <step time="60.000" loaded="21" inserted="21" running="21" waiting="0" ended="0" arrived="0" collisions="0" teleports="0" halting="1" stopped="0" meanWaitingTime="0.000000" meanTravelTime="-1.000000" meanSpeed="12.938571" meanSpeedRelative="0.931503" duration="0"/>
    <step time="61.000" loaded="21" inserted="21" running="21" waiting="0" ended="0" arrived="0" collisions="0" teleports="0" halting="0" stopped="0" meanWaitingTime="0.000000" meanTravelTime="-1.000000" meanSpeed="13.052857" meanSpeedRelative="0.939731" duration="0"/>
    <step time="62.000" loaded="21" inserted="21" running="21" waiting="0" ended="0" arrived="0" collisions="0" teleports="0" halting="0" stopped="0" meanWaitingTime="0.000000" meanTravelTime="-1.000000" meanSpeed="13.424286" meanSpeedRelative="0.966471" duration="0"/>
    <step time="63.000" loaded="22" inserted="22" running="22" waiting="0" ended="0" arrived="0" collisions="0" teleports="0" halting="1" stopped="0" meanWaitingTime="0.000000" meanTravelTime="-1.000000" meanSpeed="12.981818" meanSpeedRelative="0.934616" duration="0"/>
    <step time="64.000" loaded="22" inserted="22" running="22" waiting="0" ended="0" arrived="0" collisions="0" teleports="0" halting="0" stopped="0" meanWaitingTime="0.000000" meanTravelTime="-1.000000" meanSpeed="13.090909" meanSpeedRelative="0.942470" duration="0"/>
    <step time="65.000" loaded="22" inserted="22" running="22" waiting="0" ended="0" arrived="0" collisions="0" teleports="0" halting="0" stopped="0" meanWaitingTime="0.000000" meanTravelTime="-1.000000" meanSpeed="13.445455" meanSpeedRelative="0.967995" duration="0"/>
    <step time="66.000" loaded="23" inserted="23" running="23" waiting="0" ended="0" arrived="0" collisions="0" teleports="0" halting="1" stopped="0" meanWaitingTime="0.000000" meanTravelTime="-1.000000" meanSpeed="13.021304" meanSpeedRelative="0.937459" duration="0"/>
    <step time="67.000" loaded="23" inserted="23" running="23" waiting="0" ended="0" arrived="0" collisions="0" teleports="0" halting="0" stopped="0" meanWaitingTime="0.000000" meanTravelTime="-1.000000" meanSpeed="13.125652" meanSpeedRelative="0.944971" duration="0"/>
    <step time="68.000" loaded="23" inserted="23" running="23" waiting="0" ended="0" arrived="0" collisions="0" teleports="0" halting="0" stopped="0" meanWaitingTime="0.000000" meanTravelTime="-1.000000" meanSpeed="13.464783" meanSpeedRelative="0.969387" duration="0"/>
    <step time="69.000" loaded="24" inserted="24" running="24" waiting="0" ended="0" arrived="0" collisions="0" teleports="0" halting="1" stopped="0" meanWaitingTime="0.000000" meanTravelTime="-1.000000" meanSpeed="13.057500" meanSpeedRelative="0.940065" duration="0"/>
    <step time="70.000" loaded="24" inserted="24" running="24" waiting="0" ended="0" arrived="0" collisions="0" teleports="0" halting="0" stopped="0" meanWaitingTime="0.000000" meanTravelTime="-1.000000" meanSpeed="13.157500" meanSpeedRelative="0.947264" duration="0"/>
    <step time="71.000" loaded="24" inserted="24" running="24" waiting="0" ended="0" arrived="0" collisions="0" teleports="0" halting="0" stopped="0" meanWaitingTime="0.000000" meanTravelTime="-1.000000" meanSpeed="13.482500" meanSpeedRelative="0.970662" duration="0"/>
    <step time="72.000" loaded="25" inserted="25" running="25" waiting="0" ended="0" arrived="0" collisions="0" teleports="0" halting="1" stopped="0" meanWaitingTime="0.000000" meanTravelTime="-1.000000" meanSpeed="13.090800" meanSpeedRelative="0.942462" duration="0"/>
    <step time="73.000" loaded="25" inserted="25" running="25" waiting="0" ended="0" arrived="0" collisions="0" teleports="0" halting="0" stopped="0" meanWaitingTime="0.000000" meanTravelTime="-1.000000" meanSpeed="13.186800" meanSpeedRelative="0.949374" duration="0"/>
    <step time="74.000" loaded="25" inserted="25" running="25" waiting="0" ended="0" arrived="0" collisions="0" teleports="0" halting="0" stopped="0" meanWaitingTime="0.000000" meanTravelTime="-1.000000" meanSpeed="13.498800" meanSpeedRelative="0.971836" duration="0"/>
    <step time="75.000" loaded="26" inserted="26" running="26" waiting="0" ended="0" arrived="0" collisions="0" teleports="0" halting="1" stopped="0" meanWaitingTime="0.000000" meanTravelTime="-1.000000" meanSpeed="13.121538" meanSpeedRelative="0.944675" duration="0"/>
    <step time="76.000" loaded="26" inserted="26" running="26" waiting="0" ended="0" arrived="0" collisions="0" teleports="0" halting="0" stopped="0" meanWaitingTime="0.000000" meanTravelTime="-1.000000" meanSpeed="13.213846" meanSpeedRelative="0.951321" duration="0"/>
    <step time="77.000" loaded="26" inserted="26" running="26" waiting="0" ended="0" arrived="0" collisions="0" teleports="0" halting="0" stopped="0" meanWaitingTime="0.000000" meanTravelTime="-1.000000" meanSpeed="13.513846" meanSpeedRelative="0.972919" duration="0"/>
    <step time="78.000" loaded="27" inserted="27" running="27" waiting="0" ended="0" arrived="0" collisions="0" teleports="0" halting="1" stopped="0" meanWaitingTime="0.000000" meanTravelTime="-1.000000" meanSpeed="13.150000" meanSpeedRelative="0.946724" duration="0"/>
    <step time="79.000" loaded="27" inserted="27" running="27" waiting="0" ended="0" arrived="0" collisions="0" teleports="0" halting="0" stopped="0" meanWaitingTime="0.000000" meanTravelTime="-1.000000" meanSpeed="13.238889" meanSpeedRelative="0.953124" duration="0"/>
    <step time="80.000" loaded="27" inserted="27" running="27" waiting="0" ended="0" arrived="0" collisions="0" teleports="0" halting="0" stopped="0" meanWaitingTime="0.000000" meanTravelTime="-1.000000" meanSpeed="13.527778" meanSpeedRelative="0.973922" duration="0"/>
    <step time="81.000" loaded="28" inserted="28" running="28" waiting="0" ended="0" arrived="0" collisions="0" teleports="0" halting="1" stopped="0" meanWaitingTime="0.000000" meanTravelTime="-1.000000" meanSpeed="13.176429" meanSpeedRelative="0.948627" duration="0"/>
    <step time="82.000" loaded="28" inserted="28" running="28" waiting="0" ended="0" arrived="0" collisions="0" teleports="0" halting="0" stopped="0" meanWaitingTime="0.000000" meanTravelTime="-1.000000" meanSpeed="13.262143" meanSpeedRelative="0.954798" duration="0"/>
    <step time="83.000" loaded="28" inserted="28" running="28" waiting="0" ended="0" arrived="0" collisions="0" teleports="0" halting="0" stopped="0" meanWaitingTime="0.000000" meanTravelTime="-1.000000" meanSpeed="13.540714" meanSpeedRelative="0.974853" duration="0"/>
    <step time="84.000" loaded="29" inserted="29" running="29" waiting="0" ended="0" arrived="0" collisions="0" teleports="0" halting="1" stopped="0" meanWaitingTime="0.000000" meanTravelTime="-1.000000" meanSpeed="13.201034" meanSpeedRelative="0.950398" duration="0"/>
    <step time="85.000" loaded="29" inserted="29" running="29" waiting="0" ended="0" arrived="0" collisions="0" teleports="0" halting="0" stopped="0" meanWaitingTime="0.000000" meanTravelTime="-1.000000" meanSpeed="13.283793" meanSpeedRelative="0.956357" duration="0"/>
    <step time="86.000" loaded="29" inserted="29" running="29" waiting="0" ended="0" arrived="0" collisions="0" teleports="0" halting="0" stopped="0" meanWaitingTime="0.000000" meanTravelTime="-1.000000" meanSpeed="13.552759" meanSpeedRelative="0.975721" duration="1"/>
    <step time="87.000" loaded="30" inserted="30" running="30" waiting="0" ended="0" arrived="0" collisions="0" teleports="0" halting="1" stopped="0" meanWaitingTime="0.000000" meanTravelTime="-1.000000" meanSpeed="13.224000" meanSpeedRelative="0.952052" duration="0"/>
    <step time="88.000" loaded="30" inserted="30" running="30" waiting="0" ended="0" arrived="0" collisions="0" teleports="0" halting="0" stopped="0" meanWaitingTime="0.000000" meanTravelTime="-1.000000" meanSpeed="13.304000" meanSpeedRelative="0.957811" duration="0"/>
    <step time="89.000" loaded="30" inserted="30" running="30" waiting="0" ended="0" arrived="0" collisions="0" teleports="0" halting="0" stopped="0" meanWaitingTime="0.000000" meanTravelTime="-1.000000" meanSpeed="13.482333" meanSpeedRelative="0.970650" duration="0"/>
    <step time="90.000" loaded="31" inserted="31" running="31" waiting="0" ended="0" arrived="0" collisions="0" teleports="0" halting="1" stopped="0" meanWaitingTime="0.000000" meanTravelTime="-1.000000" meanSpeed="13.021290" meanSpeedRelative="0.937458" duration="0"/>
    <step time="91.000" loaded="31" inserted="31" running="31" waiting="0" ended="0" arrived="0" collisions="0" teleports="0" halting="0" stopped="0" meanWaitingTime="0.000000" meanTravelTime="-1.000000" meanSpeed="13.063298" meanSpeedRelative="0.940482" duration="0"/>
    <step time="92.000" loaded="31" inserted="31" running="31" waiting="0" ended="0" arrived="0" collisions="0" teleports="0" halting="0" stopped="0" meanWaitingTime="0.000000" meanTravelTime="-1.000000" meanSpeed="13.336093" meanSpeedRelative="0.960122" duration="0"/>
    <step time="93.000" loaded="32" inserted="32" running="32" waiting="0" ended="0" arrived="0" collisions="0" teleports="0" halting="1" stopped="0" meanWaitingTime="0.000000" meanTravelTime="-1.000000" meanSpeed="12.975277" meanSpeedRelative="0.934145" duration="0"/>
    <step time="94.000" loaded="32" inserted="32" running="32" waiting="0" ended="0" arrived="0" collisions="0" teleports="0" halting="0" stopped="0" meanWaitingTime="0.000000" meanTravelTime="-1.000000" meanSpeed="13.030312" meanSpeedRelative="0.938107" duration="1"/>
    <step time="95.000" loaded="32" inserted="32" running="32" waiting="0" ended="0" arrived="0" collisions="0" teleports="0" halting="0" stopped="0" meanWaitingTime="0.000000" meanTravelTime="-1.000000" meanSpeed="13.278750" meanSpeedRelative="0.955994" duration="0"/>
    <step time="96.000" loaded="33" inserted="33" running="33" waiting="0" ended="0" arrived="0" collisions="0" teleports="0" halting="1" stopped="0" meanWaitingTime="0.000000" meanTravelTime="-1.000000" meanSpeed="12.930606" meanSpeedRelative="0.930929" duration="0"/>
    <step time="97.000" loaded="33" inserted="33" running="33" waiting="0" ended="0" arrived="0" collisions="0" teleports="0" halting="0" stopped="0" meanWaitingTime="0.000000" meanTravelTime="-1.000000" meanSpeed="13.048856" meanSpeedRelative="0.939442" duration="0"/>
    <step time="98.000" loaded="33" inserted="33" running="33" waiting="0" ended="0" arrived="0" collisions="0" teleports="0" halting="0" stopped="0" meanWaitingTime="0.000000" meanTravelTime="-1.000000" meanSpeed="13.369663" meanSpeedRelative="0.962539" duration="0"/>
    <step time="99.000" loaded="34" inserted="34" running="34" waiting="0" ended="0" arrived="0" collisions="0" teleports="0" halting="1" stopped="0" meanWaitingTime="0.000000" meanTravelTime="-1.000000" meanSpeed="13.029085" meanSpeedRelative="0.938019" duration="0"/>
    <step time="100.000" loaded="34" inserted="34" running="34" waiting="0" ended="0" arrived="0" collisions="0" teleports="0" halting="0" stopped="0" meanWaitingTime="0.000000" meanTravelTime="-1.000000" meanSpeed="13.080882" meanSpeedRelative="0.941748" duration="0"/>
    <step time="101.000" loaded="34" inserted="34" running="34" waiting="0" ended="0" arrived="0" collisions="0" teleports="0" halting="0" stopped="0" meanWaitingTime="0.000000" meanTravelTime="-1.000000" meanSpeed="13.314706" meanSpeedRelative="0.958582" duration="0"/>
    <step time="102.000" loaded="35" inserted="35" running="35" waiting="0" ended="0" arrived="0" collisions="0" teleports="0" halting="1" stopped="0" meanWaitingTime="0.000000" meanTravelTime="-1.000000" meanSpeed="12.985429" meanSpeedRelative="0.934876" duration="0"/>
    <step time="103.000" loaded="35" inserted="35" running="35" waiting="0" ended="0" arrived="0" collisions="0" teleports="0" halting="0" stopped="0" meanWaitingTime="0.000000" meanTravelTime="-1.000000" meanSpeed="13.096921" meanSpeedRelative="0.942903" duration="0"/>
    <step time="104.000" loaded="35" inserted="35" running="35" waiting="0" ended="0" arrived="0" collisions="0" teleports="0" halting="0" stopped="0" meanWaitingTime="0.000000" meanTravelTime="-1.000000" meanSpeed="13.399396" meanSpeedRelative="0.964679" duration="0"/>
    <step time="105.000" loaded="36" inserted="36" running="36" waiting="0" ended="0" arrived="0" collisions="0" teleports="0" halting="1" stopped="0" meanWaitingTime="0.000000" meanTravelTime="-1.000000" meanSpeed="13.076913" meanSpeedRelative="0.941462" duration="1"/>
    <step time="106.000" loaded="36" inserted="36" running="36" waiting="0" ended="0" arrived="0" collisions="0" teleports="0" halting="0" stopped="0" meanWaitingTime="0.000000" meanTravelTime="-1.000000" meanSpeed="13.125833" meanSpeedRelative="0.944984" duration="0"/>
    <step time="107.000" loaded="36" inserted="36" running="36" waiting="0" ended="0" arrived="0" collisions="0" teleports="0" halting="0" stopped="0" meanWaitingTime="0.000000" meanTravelTime="-1.000000" meanSpeed="13.346667" meanSpeedRelative="0.960883" duration="0"/>
    <step time="108.000" loaded="37" inserted="37" running="37" waiting="0" ended="0" arrived="0" collisions="0" teleports="0" halting="1" stopped="0" meanWaitingTime="0.000000" meanTravelTime="-1.000000" meanSpeed="13.034324" meanSpeedRelative="0.938396" duration="0"/>
    <step time="109.000" loaded="37" inserted="37" running="37" waiting="0" ended="0" arrived="0" collisions="0" teleports="0" halting="0" stopped="0" meanWaitingTime="0.000000" meanTravelTime="-1.000000" meanSpeed="13.139791" meanSpeedRelative="0.945989" duration="0"/>
    <step time="110.000" loaded="37" inserted="37" running="37" waiting="0" ended="0" arrived="0" collisions="0" teleports="0" halting="0" stopped="0" meanWaitingTime="0.000000" meanTravelTime="-1.000000" meanSpeed="13.425916" meanSpeedRelative="0.966589" duration="0"/>
    <step time="111.000" loaded="38" inserted="38" running="38" waiting="0" ended="0" arrived="0" collisions="0" teleports="0" halting="1" stopped="0" meanWaitingTime="0.000000" meanTravelTime="-1.000000" meanSpeed="13.119707" meanSpeedRelative="0.944543" duration="0"/>
    <step time="112.000" loaded="38" inserted="38" running="38" waiting="0" ended="0" arrived="0" collisions="0" teleports="0" halting="0" stopped="0" meanWaitingTime="0.000000" meanTravelTime="-1.000000" meanSpeed="13.166053" meanSpeedRelative="0.947880" duration="0"/>
    <step time="113.000" loaded="38" inserted="38" running="38" waiting="0" ended="0" arrived="0" collisions="0" teleports="0" halting="0" stopped="0" meanWaitingTime="0.000000" meanTravelTime="-1.000000" meanSpeed="13.375263" meanSpeedRelative="0.962942" duration="0"/>
    <step time="114.000" loaded="39" inserted="39" running="39" waiting="0" ended="0" arrived="0" collisions="0" teleports="0" halting="1" stopped="0" meanWaitingTime="0.000000" meanTravelTime="-1.000000" meanSpeed="13.078205" meanSpeedRelative="0.941555" duration="0"/>
    <step time="115.000" loaded="39" inserted="39" running="39" waiting="0" ended="0" arrived="0" collisions="0" teleports="0" halting="0" stopped="0" meanWaitingTime="0.000000" meanTravelTime="-1.000000" meanSpeed="13.178263" meanSpeedRelative="0.948759" duration="0"/>
    <step time="116.000" loaded="39" inserted="39" running="39" waiting="0" ended="0" arrived="0" collisions="0" teleports="0" halting="0" stopped="0" meanWaitingTime="0.000000" meanTravelTime="-1.000000" meanSpeed="13.449715" meanSpeedRelative="0.968302" duration="0"/>
    <step time="117.000" loaded="40" inserted="40" running="40" waiting="0" ended="0" arrived="0" collisions="0" teleports="0" halting="1" stopped="0" meanWaitingTime="0.000000" meanTravelTime="-1.000000" meanSpeed="13.158222" meanSpeedRelative="0.947316" duration="0"/>
    <step time="118.000" loaded="40" inserted="40" running="40" waiting="0" ended="0" arrived="0" collisions="0" teleports="0" halting="0" stopped="0" meanWaitingTime="0.000000" meanTravelTime="-1.000000" meanSpeed="13.202250" meanSpeedRelative="0.950486" duration="0"/>
    <step time="119.000" loaded="40" inserted="40" running="40" waiting="0" ended="0" arrived="0" collisions="0" teleports="0" halting="0" stopped="0" meanWaitingTime="0.000000" meanTravelTime="-1.000000" meanSpeed="13.401000" meanSpeedRelative="0.964795" duration="0"/>
    <step time="120.000" loaded="40" inserted="40" running="40" waiting="0" ended="0" arrived="0" collisions="0" teleports="0" halting="0" stopped="0" meanWaitingTime="0.000000" meanTravelTime="-1.000000" meanSpeed="13.445750" meanSpeedRelative="0.968017" duration="0"/>
    <step time="121.000" loaded="40" inserted="40" running="40" waiting="0" ended="0" arrived="0" collisions="0" teleports="0" halting="0" stopped="0" meanWaitingTime="0.000000" meanTravelTime="-1.000000" meanSpeed="13.478306" meanSpeedRelative="0.970360" duration="0"/>
    <step time="122.000" loaded="40" inserted="40" running="40" waiting="0" ended="0" arrived="0" collisions="0" teleports="0" halting="0" stopped="0" meanWaitingTime="0.000000" meanTravelTime="-1.000000" meanSpeed="13.677972" meanSpeedRelative="0.984735" duration="0"/>
    <step time="123.000" loaded="40" inserted="40" running="40" waiting="0" ended="0" arrived="0" collisions="0" teleports="0" halting="0" stopped="0" meanWaitingTime="0.000000" meanTravelTime="-1.000000" meanSpeed="13.657722" meanSpeedRelative="0.983277" duration="0"/>
    <step time="124.000" loaded="40" inserted="40" running="40" waiting="0" ended="0" arrived="0" collisions="0" teleports="0" halting="0" stopped="0" meanWaitingTime="0.000000" meanTravelTime="-1.000000" meanSpeed="13.571750" meanSpeedRelative="0.977088" duration="0"/>
    <step time="125.000" loaded="40" inserted="40" running="40" waiting="0" ended="0" arrived="0" collisions="0" teleports="0" halting="0" stopped="0" meanWaitingTime="0.000000" meanTravelTime="-1.000000" meanSpeed="13.640500" meanSpeedRelative="0.982037" duration="0"/>
    <step time="126.000" loaded="40" inserted="40" running="40" waiting="0" ended="0" arrived="0" collisions="0" teleports="0" halting="0" stopped="0" meanWaitingTime="0.000000" meanTravelTime="-1.000000" meanSpeed="13.598000" meanSpeedRelative="0.978978" duration="1"/>
    <step time="127.000" loaded="40" inserted="40" running="40" waiting="0" ended="0" arrived="0" collisions="0" teleports="0" halting="0" stopped="0" meanWaitingTime="0.000000" meanTravelTime="-1.000000" meanSpeed="13.565556" meanSpeedRelative="0.976642" duration="0"/>
    <step time="128.000" loaded="40" inserted="40" running="40" waiting="0" ended="0" arrived="0" collisions="0" teleports="0" halting="0" stopped="0" meanWaitingTime="0.000000" meanTravelTime="-1.000000" meanSpeed="13.700222" meanSpeedRelative="0.986337" duration="0"/>
    <step time="129.000" loaded="40" inserted="40" running="40" waiting="0" ended="0" arrived="0" collisions="0" teleports="0" halting="0" stopped="0" meanWaitingTime="0.000000" meanTravelTime="-1.000000" meanSpeed="13.657722" meanSpeedRelative="0.983277" duration="0"/>
    <step time="130.000" loaded="40" inserted="40" running="40" waiting="0" ended="0" arrived="0" collisions="0" teleports="0" halting="0" stopped="0" meanWaitingTime="0.000000" meanTravelTime="-1.000000" meanSpeed="13.571750" meanSpeedRelative="0.977088" duration="0"/>
    <step time="131.000" loaded="40" inserted="40" running="40" waiting="0" ended="0" arrived="0" collisions="0" teleports="0" halting="0" stopped="0" meanWaitingTime="0.000000" meanTravelTime="-1.000000" meanSpeed="13.640500" meanSpeedRelative="0.982037" duration="0"/>
    <step time="132.000" loaded="40" inserted="40" running="40" waiting="0" ended="0" arrived="0" collisions="0" teleports="0" halting="0" stopped="0" meanWaitingTime="0.000000" meanTravelTime="-1.000000" meanSpeed="13.598000" meanSpeedRelative="0.978978" duration="0"/>
    <step time="133.000" loaded="40" inserted="40" running="40" waiting="0" ended="0" arrived="0" collisions="0" teleports="0" halting="0" stopped="0" meanWaitingTime="0.000000" meanTravelTime="-1.000000" meanSpeed="13.565556" meanSpeedRelative="0.976642" duration="0"/>
    <step time="134.000" loaded="40" inserted="40" running="40" waiting="0" ended="0" arrived="0" collisions="0" teleports="0" halting="0" stopped="0" meanWaitingTime="0.000000" meanTravelTime="-1.000000" meanSpeed="13.700222" meanSpeedRelative="0.986337" duration="1"/>
    <step time="135.000" loaded="40" inserted="40" running="40" waiting="0" ended="0" arrived="0" collisions="0" teleports="0" halting="0" stopped="0" meanWaitingTime="0.000000" meanTravelTime="-1.000000" meanSpeed="13.643472" meanSpeedRelative="0.982251" duration="0"/>
    <step time="136.000" loaded="40" inserted="40" running="40" waiting="0" ended="0" arrived="0" collisions="0" teleports="0" halting="0" stopped="0" meanWaitingTime="0.000000" meanTravelTime="-1.000000" meanSpeed="13.501750" meanSpeedRelative="0.972048" duration="0"/>
    <step time="137.000" loaded="40" inserted="40" running="40" waiting="0" ended="0" arrived="0" collisions="0" teleports="0" halting="0" stopped="0" meanWaitingTime="0.000000" meanTravelTime="-1.000000" meanSpeed="13.635500" meanSpeedRelative="0.981677" duration="0"/>
    <step time="138.000" loaded="40" inserted="40" running="40" waiting="0" ended="0" arrived="0" collisions="0" teleports="0" halting="0" stopped="0" meanWaitingTime="0.000000" meanTravelTime="-1.000000" meanSpeed="13.598000" meanSpeedRelative="0.978978" duration="0"/>
    <step time="139.000" loaded="40" inserted="40" running="40" waiting="0" ended="0" arrived="0" collisions="0" teleports="0" halting="0" stopped="0" meanWaitingTime="0.000000" meanTravelTime="-1.000000" meanSpeed="13.495556" meanSpeedRelative="0.971602" duration="1"/>
    <step time="140.000" loaded="40" inserted="40" running="40" waiting="0" ended="0" arrived="0" collisions="0" teleports="0" halting="0" stopped="0" meanWaitingTime="0.000000" meanTravelTime="-1.000000" meanSpeed="13.630222" meanSpeedRelative="0.981297" duration="0"/>
    <step time="141.000" loaded="40" inserted="40" running="40" waiting="0" ended="0" arrived="0" collisions="0" teleports="0" halting="0" stopped="0" meanWaitingTime="0.000000" meanTravelTime="-1.000000" meanSpeed="13.638472" meanSpeedRelative="0.981891" duration="0"/>
    <step time="142.000" loaded="40" inserted="40" running="40" waiting="0" ended="0" arrived="0" collisions="0" teleports="0" halting="0" stopped="0" meanWaitingTime="0.000000" meanTravelTime="-1.000000" meanSpeed="13.501750" meanSpeedRelative="0.972048" duration="0"/>
    <step time="143.000" loaded="40" inserted="40" running="40" waiting="0" ended="0" arrived="0" collisions="0" teleports="0" halting="0" stopped="0" meanWaitingTime="0.000000" meanTravelTime="-1.000000" meanSpeed="13.635500" meanSpeedRelative="0.981677" duration="0"/>
    <step time="144.000" loaded="40" inserted="40" running="40" waiting="0" ended="0" arrived="0" collisions="0" teleports="0" halting="0" stopped="0" meanWaitingTime="0.000000" meanTravelTime="-1.000000" meanSpeed="13.598000" meanSpeedRelative="0.978978" duration="0"/>
    <step time="145.000" loaded="40" inserted="40" running="40" waiting="0" ended="0" arrived="0" collisions="0" teleports="0" halting="0" stopped="0" meanWaitingTime="0.000000" meanTravelTime="-1.000000" meanSpeed="13.495556" meanSpeedRelative="0.971602" duration="0"/>
    <step time="146.000" loaded="40" inserted="40" running="40" waiting="0" ended="0" arrived="0" collisions="0" teleports="0" halting="0" stopped="0" meanWaitingTime="0.000000" meanTravelTime="-1.000000" meanSpeed="13.630222" meanSpeedRelative="0.981297" duration="0"/>
    <step time="147.000" loaded="40" inserted="40" running="40" waiting="0" ended="0" arrived="0" collisions="0" teleports="0" halting="0" stopped="0" meanWaitingTime="0.000000" meanTravelTime="-1.000000" meanSpeed="13.638472" meanSpeedRelative="0.981891" duration="1"/>
    <step time="148.000" loaded="40" inserted="40" running="40" waiting="0" ended="0" arrived="0" collisions="0" teleports="0" halting="0" stopped="0" meanWaitingTime="0.000000" meanTravelTime="-1.000000" meanSpeed="13.501750" meanSpeedRelative="0.972048" duration="0"/>
    <step time="149.000" loaded="40" inserted="40" running="40" waiting="0" ended="0" arrived="0" collisions="0" teleports="0" halting="0" stopped="0" meanWaitingTime="0.000000" meanTravelTime="-1.000000" meanSpeed="13.635500" meanSpeedRelative="0.981677" duration="0"/>
    <step time="150.000" loaded="40" inserted="40" running="40" waiting="0" ended="0" arrived="0" collisions="0" teleports="0" halting="0" stopped="0" meanWaitingTime="0.000000" meanTravelTime="-1.000000" meanSpeed="13.598000" meanSpeedRelative="0.978978" duration="0"/>
    <step time="151.000" loaded="40" inserted="40" running="40" waiting="0" ended="0" arrived="0" collisions="0" teleports="0" halting="0" stopped="0" meanWaitingTime="0.000000" meanTravelTime="-1.000000" meanSpeed="13.495556" meanSpeedRelative="0.971602" duration="0"/>
    <step time="152.000" loaded="40" inserted="40" running="40" waiting="0" ended="0" arrived="0" collisions="0" teleports="0" halting="0" stopped="0" meanWaitingTime="0.000000" meanTravelTime="-1.000000" meanSpeed="13.630222" meanSpeedRelative="0.981297" duration="0"/>
    <step time="153.000" loaded="40" inserted="40" running="40" waiting="0" ended="0" arrived="0" collisions="0" teleports="0" halting="0" stopped="0" meanWaitingTime="0.000000" meanTravelTime="-1.000000" meanSpeed="13.638472" meanSpeedRelative="0.981891" duration="0"/>
    <step time="154.000" loaded="40" inserted="40" running="40" waiting="0" ended="0" arrived="0" collisions="0" teleports="0" halting="0" stopped="0" meanWaitingTime="0.000000" meanTravelTime="-1.000000" meanSpeed="13.501750" meanSpeedRelative="0.972048" duration="1"/>
    <step time="155.000" loaded="40" inserted="40" running="40" waiting="0" ended="0" arrived="0" collisions="0" teleports="0" halting="0" stopped="0" meanWaitingTime="0.000000" meanTravelTime="-1.000000" meanSpeed="13.635500" meanSpeedRelative="0.981677" duration="0"/>
    <step time="156.000" loaded="40" inserted="40" running="40" waiting="0" ended="0" arrived="0" collisions="0" teleports="0" halting="0" stopped="0" meanWaitingTime="0.000000" meanTravelTime="-1.000000" meanSpeed="13.598000" meanSpeedRelative="0.978978" duration="0"/>
    <step time="157.000" loaded="40" inserted="40" running="40" waiting="0" ended="0" arrived="0" collisions="0" teleports="0" halting="0" stopped="0" meanWaitingTime="0.000000" meanTravelTime="-1.000000" meanSpeed="13.495556" meanSpeedRelative="0.971602" duration="0"/>
    <step time="158.000" loaded="40" inserted="40" running="40" waiting="0" ended="0" arrived="0" collisions="0" teleports="0" halting="0" stopped="0" meanWaitingTime="0.000000" meanTravelTime="-1.000000" meanSpeed="13.630222" meanSpeedRelative="0.981297" duration="0"/>
    <step time="159.000" loaded="40" inserted="40" running="40" waiting="0" ended="0" arrived="0" collisions="0" teleports="0" halting="0" stopped="0" meanWaitingTime="0.000000" meanTravelTime="-1.000000" meanSpeed="13.638472" meanSpeedRelative="0.981891" duration="0"/>
    <step time="160.000" loaded="40" inserted="40" running="40" waiting="0" ended="0" arrived="0" collisions="0" teleports="0" halting="0" stopped="0" meanWaitingTime="0.000000" meanTravelTime="-1.000000" meanSpeed="13.501750" meanSpeedRelative="0.972048" duration="0"/>
    <step time="161.000" loaded="40" inserted="40" running="40" waiting="0" ended="0" arrived="0" collisions="0" teleports="0" halting="0" stopped="0" meanWaitingTime="0.000000" meanTravelTime="-1.000000" meanSpeed="13.635500" meanSpeedRelative="0.981677" duration="1"/>
    <step time="162.000" loaded="40" inserted="40" running="40" waiting="0" ended="0" arrived="0" collisions="0" teleports="0" halting="0" stopped="0" meanWaitingTime="0.000000" meanTravelTime="-1.000000" meanSpeed="13.598000" meanSpeedRelative="0.978978" duration="0"/>
    <step time="163.000" loaded="40" inserted="40" running="40" waiting="0" ended="0" arrived="0" collisions="0" teleports="0" halting="0" stopped="0" meanWaitingTime="0.000000" meanTravelTime="-1.000000" meanSpeed="13.495556" meanSpeedRelative="0.971602" duration="0"/>
    <step time="164.000" loaded="40" inserted="40" running="40" waiting="0" ended="0" arrived="0" collisions="0" teleports="0" halting="0" stopped="0" meanWaitingTime="0.000000" meanTravelTime="-1.000000" meanSpeed="13.630222" meanSpeedRelative="0.981297" duration="0"/>
    <step time="165.000" loaded="40" inserted="40" running="40" waiting="0" ended="0" arrived="0" collisions="0" teleports="0" halting="0" stopped="0" meanWaitingTime="0.000000" meanTravelTime="-1.000000" meanSpeed="13.638472" meanSpeedRelative="0.981891" duration="0"/>
    <step time="166.000" loaded="40" inserted="40" running="40" waiting="0" ended="0" arrived="0" collisions="0" teleports="0" halting="0" stopped="0" meanWaitingTime="0.000000" meanTravelTime="-1.000000" meanSpeed="13.571750" meanSpeedRelative="0.977088" duration="0"/>
    <step time="167.000" loaded="40" inserted="40" running="40" waiting="0" ended="0" arrived="0" collisions="0" teleports="0" halting="0" stopped="0" meanWaitingTime="0.000000" meanTravelTime="-1.000000" meanSpeed="13.640500" meanSpeedRelative="0.982037" duration="0"/>
    <step time="168.000" loaded="40" inserted="40" running="40" waiting="0" ended="0" arrived="0" collisions="0" teleports="0" halting="0" stopped="0" meanWaitingTime="0.000000" meanTravelTime="-1.000000" meanSpeed="13.598000" meanSpeedRelative="0.978978" duration="1"/>
    <step time="169.000" loaded="40" inserted="40" running="40" waiting="0" ended="0" arrived="0" collisions="0" teleports="0" halting="0" stopped="0" meanWaitingTime="0.000000" meanTravelTime="-1.000000" meanSpeed="13.565556" meanSpeedRelative="0.976642" duration="0"/>
    <step time="170.000" loaded="40" inserted="40" running="40" waiting="0" ended="0" arrived="0" collisions="0" teleports="0" halting="0" stopped="0" meanWaitingTime="0.000000" meanTravelTime="-1.000000" meanSpeed="13.635222" meanSpeedRelative="0.981657" duration="0"/>
    <step time="171.000" loaded="40" inserted="40" running="40" waiting="0" ended="0" arrived="0" collisions="0" teleports="0" halting="0" stopped="0" meanWaitingTime="0.000000" meanTravelTime="-1.000000" meanSpeed="13.638472" meanSpeedRelative="0.981891" duration="0"/>
    <step time="172.000" loaded="40" inserted="40" running="39" waiting="0" ended="1" arrived="1" collisions="0" teleports="0" halting="0" stopped="0" meanWaitingTime="0.000000" meanTravelTime="172.000000" meanSpeed="13.563590" meanSpeedRelative="0.976500" duration="0"/>
    <step time="173.000" loaded="40" inserted="40" running="39" waiting="0" ended="1" arrived="1" collisions="0" teleports="0" halting="0" stopped="0" meanWaitingTime="0.000000" meanTravelTime="172.000000" meanSpeed="13.634103" meanSpeedRelative="0.981577" duration="0"/>
    <step time="174.000" loaded="40" inserted="40" running="39" waiting="0" ended="1" arrived="1" collisions="0" teleports="0" halting="0" stopped="0" meanWaitingTime="0.000000" meanTravelTime="172.000000" meanSpeed="13.590513" meanSpeedRelative="0.978439" duration="0"/>
    <step time="175.000" loaded="40" inserted="40" running="39" waiting="0" ended="1" arrived="1" collisions="0" teleports="0" halting="0" stopped="0" meanWaitingTime="0.000000" meanTravelTime="172.000000" meanSpeed="13.557237" meanSpeedRelative="0.976043" duration="1"/>
    <step time="176.000" loaded="40" inserted="40" running="38" waiting="0" ended="2" arrived="2" collisions="0" teleports="0" halting="0" stopped="0" meanWaitingTime="0.000000" meanTravelTime="172.500000" meanSpeed="13.621812" meanSpeedRelative="0.980692" duration="0"/>
    <step time="177.000" loaded="40" inserted="40" running="38" waiting="0" ended="2" arrived="2" collisions="0" teleports="0" halting="0" stopped="0" meanWaitingTime="0.000000" meanTravelTime="172.500000" meanSpeed="13.625234" meanSpeedRelative="0.980938" duration="0"/>
    <step time="178.000" loaded="40" inserted="40" running="37" waiting="0" ended="3" arrived="3" collisions="0" teleports="0" halting="0" stopped="0" meanWaitingTime="0.000000" meanTravelTime="172.333333" meanSpeed="13.545946" meanSpeedRelative="0.975230" duration="0"/>
    <step time="179.000" loaded="40" inserted="40" running="37" waiting="0" ended="3" arrived="3" collisions="0" teleports="0" halting="0" stopped="0" meanWaitingTime="0.000000" meanTravelTime="172.333333" meanSpeed="13.620270" meanSpeedRelative="0.980581" duration="0"/>
    <step time="180.000" loaded="40" inserted="40" running="37" waiting="0" ended="3" arrived="3" collisions="0" teleports="0" halting="0" stopped="0" meanWaitingTime="0.000000" meanTravelTime="172.333333" meanSpeed="13.574324" meanSpeedRelative="0.977273" duration="1"/>
    <step time="181.000" loaded="40" inserted="40" running="37" waiting="0" ended="3" arrived="3" collisions="0" teleports="0" halting="0" stopped="0" meanWaitingTime="0.000000" meanTravelTime="172.333333" meanSpeed="13.539250" meanSpeedRelative="0.974748" duration="0"/>
    <step time="182.000" loaded="40" inserted="40" running="36" waiting="0" ended="4" arrived="4" collisions="0" teleports="0" halting="0" stopped="0" meanWaitingTime="0.000000" meanTravelTime="172.500000" meanSpeed="13.606913" meanSpeedRelative="0.979619" duration="0"/>
    <step time="183.000" loaded="40" inserted="40" running="36" waiting="0" ended="4" arrived="4" collisions="0" teleports="0" halting="0" stopped="0" meanWaitingTime="0.000000" meanTravelTime="172.500000" meanSpeed="13.610524" meanSpeedRelative="0.979879" duration="0"/>
    <step time="184.000" loaded="40" inserted="40" running="35" waiting="0" ended="5" arrived="5" collisions="0" teleports="0" halting="0" stopped="0" meanWaitingTime="0.000000" meanTravelTime="172.400000" meanSpeed="13.526286" meanSpeedRelative="0.973815" duration="0"/>
    <step time="185.000" loaded="40" inserted="40" running="35" waiting="0" ended="5" arrived="5" collisions="0" teleports="0" halting="0" stopped="0" meanWaitingTime="0.000000" meanTravelTime="172.400000" meanSpeed="13.604857" meanSpeedRelative="0.979471" duration="1"/>
    <step time="186.000" loaded="40" inserted="40" running="35" waiting="0" ended="5" arrived="5" collisions="0" teleports="0" halting="0" stopped="0" meanWaitingTime="0.000000" meanTravelTime="172.400000" meanSpeed="13.556286" meanSpeedRelative="0.975974" duration="0"/>
    <step time="187.000" loaded="40" inserted="40" running="35" waiting="0" ended="5" arrived="5" collisions="0" teleports="0" halting="0" stopped="0" meanWaitingTime="0.000000" meanTravelTime="172.400000" meanSpeed="13.519207" meanSpeedRelative="0.973305" duration="0"/>
    <step time="188.000" loaded="40" inserted="40" running="34" waiting="0" ended="6" arrived="6" collisions="0" teleports="0" halting="0" stopped="0" meanWaitingTime="0.000000" meanTravelTime="172.500000" meanSpeed="13.590261" meanSpeedRelative="0.978421" duration="0"/>
    <step time="189.000" loaded="40" inserted="40" running="34" waiting="0" ended="6" arrived="6" collisions="0" teleports="0" halting="0" stopped="0" meanWaitingTime="0.000000" meanTravelTime="172.500000" meanSpeed="13.594085" meanSpeedRelative="0.978696" duration="0"/>
    <step time="190.000" loaded="40" inserted="40" running="33" waiting="0" ended="7" arrived="7" collisions="0" teleports="0" halting="0" stopped="0" meanWaitingTime="0.000000" meanTravelTime="172.428571" meanSpeed="13.504242" meanSpeedRelative="0.972228" duration="0"/>
    <step time="191.000" loaded="40" inserted="40" running="33" waiting="0" ended="7" arrived="7" collisions="0" teleports="0" halting="0" stopped="0" meanWaitingTime="0.000000" meanTravelTime="172.428571" meanSpeed="13.587576" meanSpeedRelative="0.978227" duration="0"/>
    <step time="192.000" loaded="40" inserted="40" running="33" waiting="0" ended="7" arrived="7" collisions="0" teleports="0" halting="0" stopped="0" meanWaitingTime="0.000000" meanTravelTime="172.428571" meanSpeed="13.536061" meanSpeedRelative="0.974518" duration="0"/>
    <step time="193.000" loaded="40" inserted="40" running="33" waiting="0" ended="7" arrived="7" collisions="0" teleports="0" halting="0" stopped="0" meanWaitingTime="0.000000" meanTravelTime="172.428571" meanSpeed="13.496735" meanSpeedRelative="0.971687" duration="0"/>
    <step time="194.000" loaded="40" inserted="40" running="32" waiting="0" ended="8" arrived="8" collisions="0" teleports="0" halting="0" stopped="0" meanWaitingTime="0.000000" meanTravelTime="172.500000" meanSpeed="13.571527" meanSpeedRelative="0.977072" duration="0"/>
    <step time="195.000" loaded="40" inserted="40" running="32" waiting="0" ended="8" arrived="8" collisions="0" teleports="0" halting="0" stopped="0" meanWaitingTime="0.000000" meanTravelTime="172.500000" meanSpeed="13.575590" meanSpeedRelative="0.977364" duration="0"/>
    <step time="196.000" loaded="40" inserted="40" running="31" waiting="0" ended="9" arrived="9" collisions="0" teleports="0" halting="0" stopped="0" meanWaitingTime="0.000000" meanTravelTime="172.444444" meanSpeed="13.479355" meanSpeedRelative="0.970436" duration="0"/>
    <step time="197.000" loaded="40" inserted="40" running="31" waiting="0" ended="9" arrived="9" collisions="0" teleports="0" halting="0" stopped="0" meanWaitingTime="0.000000" meanTravelTime="172.444444" meanSpeed="13.568065" meanSpeedRelative="0.976822" duration="0"/>
    <step time="198.000" loaded="40" inserted="40" running="31" waiting="0" ended="9" arrived="9" collisions="0" teleports="0" halting="0" stopped="0" meanWaitingTime="0.000000" meanTravelTime="172.444444" meanSpeed="13.513226" meanSpeedRelative="0.972874" duration="0"/>
    <step time="199.000" loaded="40" inserted="40" running="31" waiting="0" ended="9" arrived="9" collisions="0" teleports="0" halting="0" stopped="0" meanWaitingTime="0.000000" meanTravelTime="172.444444" meanSpeed="13.471363" meanSpeedRelative="0.969861" duration="0"/>
    <step time="200.000" loaded="40" inserted="40" running="30" waiting="0" ended="10" arrived="10" collisions="0" teleports="0" halting="0" stopped="0" meanWaitingTime="0.000000" meanTravelTime="172.500000" meanSpeed="13.550296" meanSpeedRelative="0.975543" duration="0"/>
    <step time="201.000" loaded="40" inserted="40" running="30" waiting="0" ended="10" arrived="10" collisions="0" teleports="0" halting="0" stopped="0" meanWaitingTime="0.000000" meanTravelTime="172.500000" meanSpeed="13.554629" meanSpeedRelative="0.975855" duration="0"/>
    <step time="202.000" loaded="40" inserted="40" running="29" waiting="0" ended="11" arrived="11" collisions="0" teleports="0" halting="0" stopped="0" meanWaitingTime="0.000000" meanTravelTime="172.454545" meanSpeed="13.451034" meanSpeedRelative="0.968397" duration="0"/>
    <step time="203.000" loaded="40" inserted="40" running="29" waiting="0" ended="11" arrived="11" collisions="0" teleports="0" halting="0" stopped="0" meanWaitingTime="0.000000" meanTravelTime="172.454545" meanSpeed="13.545862" meanSpeedRelative="0.975224" duration="0"/>
    <step time="204.000" loaded="40" inserted="40" running="29" waiting="0" ended="11" arrived="11" collisions="0" teleports="0" halting="0" stopped="0" meanWaitingTime="0.000000" meanTravelTime="172.454545" meanSpeed="13.487241" meanSpeedRelative="0.971004" duration="0"/>
    <step time="205.000" loaded="40" inserted="40" running="29" waiting="0" ended="11" arrived="11" collisions="0" teleports="0" halting="0" stopped="0" meanWaitingTime="0.000000" meanTravelTime="172.454545" meanSpeed="13.442491" meanSpeedRelative="0.967782" duration="0"/>
    <step time="206.000" loaded="40" inserted="40" running="28" waiting="0" ended="12" arrived="12" collisions="0" teleports="0" halting="0" stopped="0" meanWaitingTime="0.000000" meanTravelTime="172.500000" meanSpeed="13.526031" meanSpeedRelative="0.973796" duration="0"/>
    <step time="207.000" loaded="40" inserted="40" running="28" waiting="0" ended="12" arrived="12" collisions="0" teleports="0" halting="0" stopped="0" meanWaitingTime="0.000000" meanTravelTime="172.500000" meanSpeed="13.530674" meanSpeedRelative="0.974131" duration="0"/>
    <step time="208.000" loaded="40" inserted="40" running="27" waiting="0" ended="13" arrived="13" collisions="0" teleports="0" halting="0" stopped="0" meanWaitingTime="0.000000" meanTravelTime="172.461538" meanSpeed="13.418519" meanSpeedRelative="0.966056" duration="0"/>
    <step time="209.000" loaded="40" inserted="40" running="27" waiting="0" ended="13" arrived="13" collisions="0" teleports="0" halting="0" stopped="0" meanWaitingTime="0.000000" meanTravelTime="172.461538" meanSpeed="13.611111" meanSpeedRelative="0.979922" duration="0"/>
    <step time="210.000" loaded="40" inserted="40" running="27" waiting="0" ended="13" arrived="13" collisions="0" teleports="0" halting="0" stopped="0" meanWaitingTime="0.000000" meanTravelTime="172.461538" meanSpeed="13.714815" meanSpeedRelative="0.987388" duration="0"/>
    <step time="211.000" loaded="40" inserted="40" running="27" waiting="0" ended="13" arrived="13" collisions="0" teleports="0" halting="0" stopped="0" meanWaitingTime="0.000000" meanTravelTime="172.461538" meanSpeed="13.707407" meanSpeedRelative="0.986854" duration="0"/>
    <step time="212.000" loaded="40" inserted="40" running="26" waiting="0" ended="14" arrived="14" collisions="0" teleports="0" halting="0" stopped="0" meanWaitingTime="0.000000" meanTravelTime="172.500000" meanSpeed="13.782308" meanSpeedRelative="0.992247" duration="0"/>
    <step time="213.000" loaded="40" inserted="40" running="26" waiting="0" ended="14" arrived="14" collisions="0" teleports="0" halting="0" stopped="0" meanWaitingTime="0.000000" meanTravelTime="172.500000" meanSpeed="13.860385" meanSpeedRelative="0.997868" duration="0"/>
    <step time="214.000" loaded="40" inserted="40" running="25" waiting="0" ended="15" arrived="15" collisions="0" teleports="0" halting="0" stopped="0" meanWaitingTime="0.000000" meanTravelTime="172.466667" meanSpeed="13.778000" meanSpeedRelative="0.991937" duration="0"/>
    <step time="215.000" loaded="40" inserted="40" running="25" waiting="0" ended="15" arrived="15" collisions="0" teleports="0" halting="0" stopped="0" meanWaitingTime="0.000000" meanTravelTime="172.466667" meanSpeed="13.882000" meanSpeedRelative="0.999424" duration="0"/>
    <step time="216.000" loaded="40" inserted="40" running="25" waiting="0" ended="15" arrived="15" collisions="0" teleports="0" halting="0" stopped="0" meanWaitingTime="0.000000" meanTravelTime="172.466667" meanSpeed="13.890000" meanSpeedRelative="1.000000" duration="0"/>
    <step time="217.000" loaded="40" inserted="40" running="25" waiting="0" ended="15" arrived="15" collisions="0" teleports="0" halting="0" stopped="0" meanWaitingTime="0.000000" meanTravelTime="172.466667" meanSpeed="13.778000" meanSpeedRelative="0.991937" duration="0"/>
    <step time="218.000" loaded="40" inserted="40" running="24" waiting="0" ended="16" arrived="16" collisions="0" teleports="0" halting="0" stopped="0" meanWaitingTime="0.000000" meanTravelTime="172.500000" meanSpeed="13.773333" meanSpeedRelative="0.991601" duration="0"/>
    <step time="219.000" loaded="40" inserted="40" running="24" waiting="0" ended="16" arrived="16" collisions="0" teleports="0" halting="0" stopped="0" meanWaitingTime="0.000000" meanTravelTime="172.500000" meanSpeed="13.857917" meanSpeedRelative="0.997690" duration="1"/>
    <step time="220.000" loaded="40" inserted="40" running="23" waiting="0" ended="17" arrived="17" collisions="0" teleports="0" halting="0" stopped="0" meanWaitingTime="0.000000" meanTravelTime="172.470588" meanSpeed="13.768261" meanSpeedRelative="0.991235" duration="0"/>
    <step time="221.000" loaded="40" inserted="40" running="23" waiting="0" ended="17" arrived="17" collisions="0" teleports="0" halting="0" stopped="0" meanWaitingTime="0.000000" meanTravelTime="172.470588" meanSpeed="13.881304" meanSpeedRelative="0.999374" duration="0"/>
    <step time="222.000" loaded="40" inserted="40" running="23" waiting="0" ended="17" arrived="17" collisions="0" teleports="0" halting="0" stopped="0" meanWaitingTime="0.000000" meanTravelTime="172.470588" meanSpeed="13.890000" meanSpeedRelative="1.000000" duration="0"/>
    <step time="223.000" loaded="40" inserted="40" running="23" waiting="0" ended="17" arrived="17" collisions="0" teleports="0" halting="0" stopped="0" meanWaitingTime="0.000000" meanTravelTime="172.470588" meanSpeed="13.768261" meanSpeedRelative="0.991235" duration="1"/>
    <step time="224.000" loaded="40" inserted="40" running="22" waiting="0" ended="18" arrived="18" collisions="0" teleports="0" halting="0" stopped="0" meanWaitingTime="0.000000" meanTravelTime="172.500000" meanSpeed="13.762727" meanSpeedRelative="0.990837" duration="0"/>
    <step time="225.000" loaded="40" inserted="40" running="22" waiting="0" ended="18" arrived="18" collisions="0" teleports="0" halting="0" stopped="0" meanWaitingTime="0.000000" meanTravelTime="172.500000" meanSpeed="13.855000" meanSpeedRelative="0.997480" duration="0"/>
    <step time="226.000" loaded="40" inserted="40" running="21" waiting="0" ended="19" arrived="19" collisions="0" teleports="0" halting="0" stopped="0" meanWaitingTime="0.000000" meanTravelTime="172.473684" meanSpeed="13.756667" meanSpeedRelative="0.990401" duration="0"/>
    <step time="227.000" loaded="40" inserted="40" running="21" waiting="0" ended="19" arrived="19" collisions="0" teleports="0" halting="0" stopped="0" meanWaitingTime="0.000000" meanTravelTime="172.473684" meanSpeed="13.880476" meanSpeedRelative="0.999314" duration="0"/>
    <step time="228.000" loaded="40" inserted="40" running="21" waiting="0" ended="19" arrived="19" collisions="0" teleports="0" halting="0" stopped="0" meanWaitingTime="0.000000" meanTravelTime="172.473684" meanSpeed="13.890000" meanSpeedRelative="1.000000" duration="0"/>
    <step time="229.000" loaded="40" inserted="40" running="21" waiting="0" ended="19" arrived="19" collisions="0" teleports="0" halting="0" stopped="0" meanWaitingTime="0.000000" meanTravelTime="172.473684" meanSpeed="13.756667" meanSpeedRelative="0.990401" duration="0"/>
    <step time="230.000" loaded="40" inserted="40" running="20" waiting="0" ended="20" arrived="20" collisions="0" teleports="0" halting="0" stopped="0" meanWaitingTime="0.000000" meanTravelTime="172.500000" meanSpeed="13.750000" meanSpeedRelative="0.989921" duration="0"/>
    <step time="231.000" loaded="40" inserted="40" running="20" waiting="0" ended="20" arrived="20" collisions="0" teleports="0" halting="0" stopped="0" meanWaitingTime="0.000000" meanTravelTime="172.500000" meanSpeed="13.851500" meanSpeedRelative="0.997228" duration="0"/>
    <step time="232.000" loaded="40" inserted="40" running="19" waiting="0" ended="21" arrived="21" collisions="0" teleports="0" halting="0" stopped="0" meanWaitingTime="0.000000" meanTravelTime="172.476190" meanSpeed="13.742632" meanSpeedRelative="0.989390" duration="0"/>
    <step time="233.000" loaded="40" inserted="40" running="19" waiting="0" ended="21" arrived="21" collisions="0" teleports="0" halting="0" stopped="0" meanWaitingTime="0.000000" meanTravelTime="172.476190" meanSpeed="13.879474" meanSpeedRelative="0.999242" duration="0"/>
    <step time="234.000" loaded="40" inserted="40" running="19" waiting="0" ended="21" arrived="21" collisions="0" teleports="0" halting="0" stopped="0" meanWaitingTime="0.000000" meanTravelTime="172.476190" meanSpeed="13.890000" meanSpeedRelative="1.000000" duration="0"/>
    <step time="235.000" loaded="40" inserted="40" running="19" waiting="0" ended="21" arrived="21" collisions="0" teleports="0" halting="0" stopped="0" meanWaitingTime="0.000000" meanTravelTime="172.476190" meanSpeed="13.742632" meanSpeedRelative="0.989390" duration="0"/>
    <step time="236.000" loaded="40" inserted="40" running="18" waiting="0" ended="22" arrived="22" collisions="0" teleports="0" halting="0" stopped="0" meanWaitingTime="0.000000" meanTravelTime="172.500000" meanSpeed="13.734444" meanSpeedRelative="0.988801" duration="0"/>
    <step time="237.000" loaded="40" inserted="40" running="18" waiting="0" ended="22" arrived="22" collisions="0" teleports="0" halting="0" stopped="0" meanWaitingTime="0.000000" meanTravelTime="172.500000" meanSpeed="13.847222" meanSpeedRelative="0.996920" duration="0"/>
    <step time="238.000" loaded="40" inserted="40" running="17" waiting="0" ended="23" arrived="23" collisions="0" teleports="0" halting="0" stopped="0" meanWaitingTime="0.000000" meanTravelTime="172.478261" meanSpeed="13.725294" meanSpeedRelative="0.988142" duration="0"/>
    <step time="239.000" loaded="40" inserted="40" running="17" waiting="0" ended="23" arrived="23" collisions="0" teleports="0" halting="0" stopped="0" meanWaitingTime="0.000000" meanTravelTime="172.478261" meanSpeed="13.878235" meanSpeedRelative="0.999153" duration="0"/>
    <step time="240.000" loaded="40" inserted="40" running="17" waiting="0" ended="23" arrived="23" collisions="0" teleports="0" halting="0" stopped="0" meanWaitingTime="0.000000" meanTravelTime="172.478261" meanSpeed="13.890000" meanSpeedRelative="1.000000" duration="0"/>
    <step time="241.000" loaded="40" inserted="40" running="17" waiting="0" ended="23" arrived="23" collisions="0" teleports="0" halting="0" stopped="0" meanWaitingTime="0.000000" meanTravelTime="172.478261" meanSpeed="13.725294" meanSpeedRelative="0.988142" duration="0"/>
    <step time="242.000" loaded="40" inserted="40" running="16" waiting="0" ended="24" arrived="24" collisions="0" teleports="0" halting="0" stopped="0" meanWaitingTime="0.000000" meanTravelTime="172.500000" meanSpeed="13.715000" meanSpeedRelative="0.987401" duration="0"/>
    <step time="243.000" loaded="40" inserted="40" running="16" waiting="0" ended="24" arrived="24" collisions="0" teleports="0" halting="0" stopped="0" meanWaitingTime="0.000000" meanTravelTime="172.500000" meanSpeed="13.841875" meanSpeedRelative="0.996535" duration="0"/>
    <step time="244.000" loaded="40" inserted="40" running="15" waiting="0" ended="25" arrived="25" collisions="0" teleports="0" halting="0" stopped="0" meanWaitingTime="0.000000" meanTravelTime="172.480000" meanSpeed="13.703333" meanSpeedRelative="0.986561" duration="0"/>
    <step time="245.000" loaded="40" inserted="40" running="15" waiting="0" ended="25" arrived="25" collisions="0" teleports="0" halting="0" stopped="0" meanWaitingTime="0.000000" meanTravelTime="172.480000" meanSpeed="13.876667" meanSpeedRelative="0.999040" duration="0"/>
    <step time="246.000" loaded="40" inserted="40" running="15" waiting="0" ended="25" arrived="25" collisions="0" teleports="0" halting="0" stopped="0" meanWaitingTime="0.000000" meanTravelTime="172.480000" meanSpeed="13.890000" meanSpeedRelative="1.000000" duration="0"/>
    <step time="247.000" loaded="40" inserted="40" running="15" waiting="0" ended="25" arrived="25" collisions="0" teleports="0" halting="0" stopped="0" meanWaitingTime="0.000000" meanTravelTime="172.480000" meanSpeed="13.703333" meanSpeedRelative="0.986561" duration="0"/>
    <step time="248.000" loaded="40" inserted="40" running="14" waiting="0" ended="26" arrived="26" collisions="0" teleports="0" halting="0" stopped="0" meanWaitingTime="0.000000" meanTravelTime="172.500000" meanSpeed="13.690000" meanSpeedRelative="0.985601" duration="0"/>
    <step time="249.000" loaded="40" inserted="40" running="14" waiting="0" ended="26" arrived="26" collisions="0" teleports="0" halting="0" stopped="0" meanWaitingTime="0.000000" meanTravelTime="172.500000" meanSpeed="13.835000" meanSpeedRelative="0.996040" duration="1"/>
    <step time="250.000" loaded="40" inserted="40" running="13" waiting="0" ended="27" arrived="27" collisions="0" teleports="0" halting="0" stopped="0" meanWaitingTime="0.000000" meanTravelTime="172.481481" meanSpeed="13.674615" meanSpeedRelative="0.984494" duration="0"/>
    <step time="251.000" loaded="40" inserted="40" running="13" waiting="0" ended="27" arrived="27" collisions="0" teleports="0" halting="0" stopped="0" meanWaitingTime="0.000000" meanTravelTime="172.481481" meanSpeed="13.874615" meanSpeedRelative="0.998892" duration="0"/>
    <step time="252.000" loaded="40" inserted="40" running="13" waiting="0" ended="27" arrived="27" collisions="0" teleports="0" halting="0" stopped="0" meanWaitingTime="0.000000" meanTravelTime="172.481481" meanSpeed="13.890000" meanSpeedRelative="1.000000" duration="0"/>
    <step time="253.000" loaded="40" inserted="40" running="13" waiting="0" ended="27" arrived="27" collisions="0" teleports="0" halting="0" stopped="0" meanWaitingTime="0.000000" meanTravelTime="172.481481" meanSpeed="13.674615" meanSpeedRelative="0.984494" duration="0"/>
    <step time="254.000" loaded="40" inserted="40" running="12" waiting="0" ended="28" arrived="28" collisions="0" teleports="0" halting="0" stopped="0" meanWaitingTime="0.000000" meanTravelTime="172.500000" meanSpeed="13.656667" meanSpeedRelative="0.983201" duration="0"/>
    <step time="255.000" loaded="40" inserted="40" running="12" waiting="0" ended="28" arrived="28" collisions="0" teleports="0" halting="0" stopped="0" meanWaitingTime="0.000000" meanTravelTime="172.500000" meanSpeed="13.873333" meanSpeedRelative="0.998800" duration="0"/>
    <step time="256.000" loaded="40" inserted="40" running="11" waiting="0" ended="29" arrived="29" collisions="0" teleports="0" halting="0" stopped="0" meanWaitingTime="0.000000" meanTravelTime="172.482759" meanSpeed="13.890000" meanSpeedRelative="1.000000" duration="0"/>
    <step time="257.000" loaded="40" inserted="40" running="11" waiting="0" ended="29" arrived="29" collisions="0" teleports="0" halting="0" stopped="0" meanWaitingTime="0.000000" meanTravelTime="172.482759" meanSpeed="13.890000" meanSpeedRelative="1.000000" duration="0"/>
    <step time="258.000" loaded="40" inserted="40" running="11" waiting="0" ended="29" arrived="29" collisions="0" teleports="0" halting="0" stopped="0" meanWaitingTime="0.000000" meanTravelTime="172.482759" meanSpeed="13.890000" meanSpeedRelative="1.000000" duration="1"/>
    <step time="259.000" loaded="40" inserted="40" running="11" waiting="0" ended="29" arrived="29" collisions="0" teleports="0" halting="0" stopped="0" meanWaitingTime="0.000000" meanTravelTime="172.482759" meanSpeed="13.890000" meanSpeedRelative="1.000000" duration="0"/>
    <step time="260.000" loaded="40" inserted="40" running="10" waiting="0" ended="30" arrived="30" collisions="0" teleports="0" halting="0" stopped="0" meanWaitingTime="0.000000" meanTravelTime="172.500000" meanSpeed="13.890000" meanSpeedRelative="1.000000" duration="0"/>
    <step time="261.000" loaded="40" inserted="40" running="10" waiting="0" ended="30" arrived="30" collisions="0" teleports="0" halting="0" stopped="0" meanWaitingTime="0.000000" meanTravelTime="172.500000" meanSpeed="13.890000" meanSpeedRelative="1.000000" duration="0"/>
    <step time="262.000" loaded="40" inserted="40" running="9" waiting="0" ended="31" arrived="31" collisions="0" teleports="0" halting="0" stopped="0" meanWaitingTime="0.000000" meanTravelTime="172.483871" meanSpeed="13.890000" meanSpeedRelative="1.000000" duration="0"/>
    <step time="263.000" loaded="40" inserted="40" running="9" waiting="0" ended="31" arrived="31" collisions="0" teleports="0" halting="0" stopped="0" meanWaitingTime="0.000000" meanTravelTime="172.483871" meanSpeed="13.890000" meanSpeedRelative="1.000000" duration="0"/>
    <step time="264.000" loaded="40" inserted="40" running="9" waiting="0" ended="31" arrived="31" collisions="0" teleports="0" halting="0" stopped="0" meanWaitingTime="0.000000" meanTravelTime="172.483871" meanSpeed="13.890000" meanSpeedRelative="1.000000" duration="0"/>
    <step time="265.000" loaded="40" inserted="40" running="9" waiting="0" ended="31" arrived="31" collisions="0" teleports="0" halting="0" stopped="0" meanWaitingTime="0.000000" meanTravelTime="172.483871" meanSpeed="13.890000" meanSpeedRelative="1.000000" duration="0"/>
    <step time="266.000" loaded="40" inserted="40" running="8" waiting="0" ended="32" arrived="32" collisions="0" teleports="0" halting="0" stopped="0" meanWaitingTime="0.000000" meanTravelTime="172.500000" meanSpeed="13.890000" meanSpeedRelative="1.000000" duration="0"/>
    <step time="267.000" loaded="40" inserted="40" running="8" waiting="0" ended="32" arrived="32" collisions="0" teleports="0" halting="0" stopped="0" meanWaitingTime="0.000000" meanTravelTime="172.500000" meanSpeed="13.890000" meanSpeedRelative="1.000000" duration="0"/>
    <step time="268.000" loaded="40" inserted="40" running="7" waiting="0" ended="33" arrived="33" collisions="0" teleports="0" halting="0" stopped="0" meanWaitingTime="0.000000" meanTravelTime="172.484848" meanSpeed="13.890000" meanSpeedRelative="1.000000" duration="0"/>
    <step time="269.000" loaded="40" inserted="40" running="7" waiting="0" ended="33" arrived="33" collisions="0" teleports="0" halting="0" stopped="0" meanWaitingTime="0.000000" meanTravelTime="172.484848" meanSpeed="13.890000" meanSpeedRelative="1.000000" duration="0"/>
    <step time="270.000" loaded="40" inserted="40" running="7" waiting="0" ended="33" arrived="33" collisions="0" teleports="0" halting="0" stopped="0" meanWaitingTime="0.000000" meanTravelTime="172.484848" meanSpeed="13.890000" meanSpeedRelative="1.000000" duration="0"/>
    <step time="271.000" loaded="40" inserted="40" running="7" waiting="0" ended="33" arrived="33" collisions="0" teleports="0" halting="0" stopped="0" meanWaitingTime="0.000000" meanTravelTime="172.484848" meanSpeed="13.890000" meanSpeedRelative="1.000000" duration="0"/>
    <step time="272.000" loaded="40" inserted="40" running="6" waiting="0" ended="34" arrived="34" collisions="0" teleports="0" halting="0" stopped="0" meanWaitingTime="0.000000" meanTravelTime="172.500000" meanSpeed="13.890000" meanSpeedRelative="1.000000" duration="0"/>
    <step time="273.000" loaded="40" inserted="40" running="6" waiting="0" ended="34" arrived="34" collisions="0" teleports="0" halting="0" stopped="0" meanWaitingTime="0.000000" meanTravelTime="172.500000" meanSpeed="13.890000" meanSpeedRelative="1.000000" duration="0"/>
    <step time="274.000" loaded="40" inserted="40" running="5" waiting="0" ended="35" arrived="35" collisions="0" teleports="0" halting="0" stopped="0" meanWaitingTime="0.000000" meanTravelTime="172.485714" meanSpeed="13.890000" meanSpeedRelative="1.000000" duration="0"/>
    <step time="275.000" loaded="40" inserted="40" running="5" waiting="0" ended="35" arrived="35" collisions="0" teleports="0" halting="0" stopped="0" meanWaitingTime="0.000000" meanTravelTime="172.485714" meanSpeed="13.890000" meanSpeedRelative="1.000000" duration="0"/>
    <step time="276.000" loaded="40" inserted="40" running="5" waiting="0" ended="35" arrived="35" collisions="0" teleports="0" halting="0" stopped="0" meanWaitingTime="0.000000" meanTravelTime="172.485714" meanSpeed="13.890000" meanSpeedRelative="1.000000" duration="0"/>
    <step time="277.000" loaded="40" inserted="40" running="5" waiting="0" ended="35" arrived="35" collisions="0" teleports="0" halting="0" stopped="0" meanWaitingTime="0.000000" meanTravelTime="172.485714" meanSpeed="13.890000" meanSpeedRelative="1.000000" duration="0"/>
    <step time="278.000" loaded="40" inserted="40" running="4" waiting="0" ended="36" arrived="36" collisions="0" teleports="0" halting="0" stopped="0" meanWaitingTime="0.000000" meanTravelTime="172.500000" meanSpeed="13.890000" meanSpeedRelative="1.000000" duration="0"/>
    <step time="279.000" loaded="40" inserted="40" running="4" waiting="0" ended="36" arrived="36" collisions="0" teleports="0" halting="0" stopped="0" meanWaitingTime="0.000000" meanTravelTime="172.500000" meanSpeed="13.890000" meanSpeedRelative="1.000000" duration="0"/>
    <step time="280.000" loaded="40" inserted="40" running="3" waiting="0" ended="37" arrived="37" collisions="0" teleports="0" halting="0" stopped="0" meanWaitingTime="0.000000" meanTravelTime="172.486486" meanSpeed="13.890000" meanSpeedRelative="1.000000" duration="0"/>
    <step time="281.000" loaded="40" inserted="40" running="3" waiting="0" ended="37" arrived="37" collisions="0" teleports="0" halting="0" stopped="0" meanWaitingTime="0.000000" meanTravelTime="172.486486" meanSpeed="13.890000" meanSpeedRelative="1.000000" duration="0"/>
    <step time="282.000" loaded="40" inserted="40" running="3" waiting="0" ended="37" arrived="37" collisions="0" teleports="0" halting="0" stopped="0" meanWaitingTime="0.000000" meanTravelTime="172.486486" meanSpeed="13.890000" meanSpeedRelative="1.000000" duration="0"/>
    <step time="283.000" loaded="40" inserted="40" running="3" waiting="0" ended="37" arrived="37" collisions="0" teleports="0" halting="0" stopped="0" meanWaitingTime="0.000000" meanTravelTime="172.486486" meanSpeed="13.890000" meanSpeedRelative="1.000000" duration="0"/>
    <step time="284.000" loaded="40" inserted="40" running="2" waiting="0" ended="38" arrived="38" collisions="0" teleports="0" halting="0" stopped="0" meanWaitingTime="0.000000" meanTravelTime="172.500000" meanSpeed="13.890000" meanSpeedRelative="1.000000" duration="0"/>
    <step time="285.000" loaded="40" inserted="40" running="2" waiting="0" ended="38" arrived="38" collisions="0" teleports="0" halting="0" stopped="0" meanWaitingTime="0.000000" meanTravelTime="172.500000" meanSpeed="13.890000" meanSpeedRelative="1.000000" duration="0"/>
    <step time="286.000" loaded="40" inserted="40" running="1" waiting="0" ended="39" arrived="39" collisions="0" teleports="0" halting="0" stopped="0" meanWaitingTime="0.000000" meanTravelTime="172.487179" meanSpeed="13.890000" meanSpeedRelative="1.000000" duration="0"/>
    <step time="287.000" loaded="40" inserted="40" running="1" waiting="0" ended="39" arrived="39" collisions="0" teleports="0" halting="0" stopped="0" meanWaitingTime="0.000000" meanTravelTime="172.487179" meanSpeed="13.890000" meanSpeedRelative="1.000000" duration="0"/>
    <step time="288.000" loaded="40" inserted="40" running="1" waiting="0" ended="39" arrived="39" collisions="0" teleports="0" halting="0" stopped="0" meanWaitingTime="0.000000" meanTravelTime="172.487179" meanSpeed="13.890000" meanSpeedRelative="1.000000" duration="0"/>
    <step time="289.000" loaded="40" inserted="40" running="1" waiting="0" ended="39" arrived="39" collisions="0" teleports="0" halting="0" stopped="0" meanWaitingTime="0.000000" meanTravelTime="172.487179" meanSpeed="13.890000" meanSpeedRelative="1.000000" duration="0"/>
    <step time="290.000" loaded="40" inserted="40" running="0" waiting="0" ended="40" arrived="40" collisions="0" teleports="0" halting="0" stopped="0" meanWaitingTime="0.000000" meanTravelTime="172.500000" meanSpeed="-1.000000" meanSpeedRelative="-1.000000" duration="0"/>
    <step time="291.000" loaded="40" inserted="40" running="0" waiting="0" ended="40" arrived="40" collisions="0" teleports="0" halting="0" stopped="0" meanWaitingTime="0.000000" meanTravelTime="172.500000" meanSpeed="-1.000000" meanSpeedRelative="-1.000000" duration="0"/>
    <step time="292.000" loaded="40" inserted="40" running="0" waiting="0" ended="40" arrived="40" collisions="0" teleports="0" halting="0" stopped="0" meanWaitingTime="0.000000" meanTravelTime="172.500000" meanSpeed="-1.000000" meanSpeedRelative="-1.000000" duration="0"/>
    <step time="293.000" loaded="40" inserted="40" running="0" waiting="0" ended="40" arrived="40" collisions="0" teleports="0" halting="0" stopped="0" meanWaitingTime="0.000000" meanTravelTime="172.500000" meanSpeed="-1.000000" meanSpeedRelative="-1.000000" duration="0"/>
    <step time="294.000" loaded="40" inserted="40" running="0" waiting="0" ended="40" arrived="40" collisions="0" teleports="0" halting="0" stopped="0" meanWaitingTime="0.000000" meanTravelTime="172.500000" meanSpeed="-1.000000" meanSpeedRelative="-1.000000" duration="0"/>
    <step time="295.000" loaded="40" inserted="40" running="0" waiting="0" ended="40" arrived="40" collisions="0" teleports="0" halting="0" stopped="0" meanWaitingTime="0.000000" meanTravelTime="172.500000" meanSpeed="-1.000000" meanSpeedRelative="-1.000000" duration="0"/>
    <step time="296.000" loaded="40" inserted="40" running="0" waiting="0" ended="40" arrived="40" collisions="0" teleports="0" halting="0" stopped="0" meanWaitingTime="0.000000" meanTravelTime="172.500000" meanSpeed="-1.000000" meanSpeedRelative="-1.000000" duration="0"/>
    <step time="297.000" loaded="40" inserted="40" running="0" waiting="0" ended="40" arrived="40" collisions="0" teleports="0" halting="0" stopped="0" meanWaitingTime="0.000000" meanTravelTime="172.500000" meanSpeed="-1.000000" meanSpeedRelative="-1.000000" duration="0"/>
    <step time="298.000" loaded="40" inserted="40" running="0" waiting="0" ended="40" arrived="40" collisions="0" teleports="0" halting="0" stopped="0" meanWaitingTime="0.000000" meanTravelTime="172.500000" meanSpeed="-1.000000" meanSpeedRelative="-1.000000" duration="0"/>
    <step time="299.000" loaded="40" inserted="40" running="0" waiting="0" ended="40" arrived="40" collisions="0" teleports="0" halting="0" stopped="0" meanWaitingTime="0.000000" meanTravelTime="172.500000" meanSpeed="-1.000000" meanSpeedRelative="-1.000000" duration="0"/>
</summary>
